DiyibenFuzaxingChuangshanghouTaliZhenghouqunZiwoLiaoyuShengjing/README.md
DiyibenFuzaxingChuangshanghouTaliZhenghouqunZiwoLiaoyuShengjing/__init__.py
DiyibenFuzaxingChuangshanghouTaliZhenghouqunZiwoLiaoyuShengjing/__main__.py
DiyibenFuzaxingChuangshanghouTaliZhenghouqunZiwoLiaoyuShengjing/file.epub
DiyibenFuzaxingChuangshanghouTaliZhenghouqunZiwoLiaoyuShengjing/index.html
DiyibenFuzaxingChuangshanghouTaliZhenghouqunZiwoLiaoyuShengjing/css/__init__.py
DiyibenFuzaxingChuangshanghouTaliZhenghouqunZiwoLiaoyuShengjing/css/annotations.css
DiyibenFuzaxingChuangshanghouTaliZhenghouqunZiwoLiaoyuShengjing/css/main.css
DiyibenFuzaxingChuangshanghouTaliZhenghouqunZiwoLiaoyuShengjing/css/normalize.css
DiyibenFuzaxingChuangshanghouTaliZhenghouqunZiwoLiaoyuShengjing/css/popup.css
DiyibenFuzaxingChuangshanghouTaliZhenghouqunZiwoLiaoyuShengjing/font/__init__.py
DiyibenFuzaxingChuangshanghouTaliZhenghouqunZiwoLiaoyuShengjing/font/fontello.eot
DiyibenFuzaxingChuangshanghouTaliZhenghouqunZiwoLiaoyuShengjing/font/fontello.svg
DiyibenFuzaxingChuangshanghouTaliZhenghouqunZiwoLiaoyuShengjing/font/fontello.ttf
DiyibenFuzaxingChuangshanghouTaliZhenghouqunZiwoLiaoyuShengjing/font/fontello.woff
DiyibenFuzaxingChuangshanghouTaliZhenghouqunZiwoLiaoyuShengjing/img/__init__.py
DiyibenFuzaxingChuangshanghouTaliZhenghouqunZiwoLiaoyuShengjing/img/annotator-glyph-sprite.png
DiyibenFuzaxingChuangshanghouTaliZhenghouqunZiwoLiaoyuShengjing/img/annotator-icon-sprite.png
DiyibenFuzaxingChuangshanghouTaliZhenghouqunZiwoLiaoyuShengjing/img/apple-touch-icon.png
DiyibenFuzaxingChuangshanghouTaliZhenghouqunZiwoLiaoyuShengjing/img/cancelfullscreen.png
DiyibenFuzaxingChuangshanghouTaliZhenghouqunZiwoLiaoyuShengjing/img/close.png
DiyibenFuzaxingChuangshanghouTaliZhenghouqunZiwoLiaoyuShengjing/img/fullscreen.png
DiyibenFuzaxingChuangshanghouTaliZhenghouqunZiwoLiaoyuShengjing/img/loader.gif
DiyibenFuzaxingChuangshanghouTaliZhenghouqunZiwoLiaoyuShengjing/img/menu-icon.png
diyiben_fuzaxing_chuangshanghou_tali_zhenghouqun_ziwo_liaoyu_shengjing-2022.10.3.0.dist-info/METADATA
diyiben_fuzaxing_chuangshanghou_tali_zhenghouqun_ziwo_liaoyu_shengjing-2022.10.3.0.dist-info/WHEEL
diyiben_fuzaxing_chuangshanghou_tali_zhenghouqun_ziwo_liaoyu_shengjing-2022.10.3.0.dist-info/entry_points.txt
diyiben_fuzaxing_chuangshanghou_tali_zhenghouqun_ziwo_liaoyu_shengjing-2022.10.3.0.dist-info/top_level.txt
diyiben_fuzaxing_chuangshanghou_tali_zhenghouqun_ziwo_liaoyu_shengjing-2022.10.3.0.dist-info/RECORD
